src/receiver/receiver.v
module receiver(RXD, clk, reset, rx_data, rx_busy);
	input	RXD;
	input	clk;
	input	reset;
	output	[0:7] rx_data;
	output	rx_busy;

	parameter waiting = 1'b0;
	parameter reading = 1'b1;

	reg [0:7]	buffer = 8'b00000000;
	reg status = waiting;

	integer count = 0;

	always @ (posedge clk)
		begin
			if(reset)
				begin
					buffer = 8'b00000000;
					status = waiting;
				end
			else if(status == waiting)
				begin
					//$display("waiting");
					if (!RXD) 
						begin
							status = reading;
							count = 0;
						end
				end
			else 
				begin
					//$display("reading");
					if(count < 8)
						begin
							buffer[count] = RXD;
							count=count+1;
						end
					else 
						begin
							status = waiting;
						end
				end
		end

		assign rx_busy = status;
		assign rx_data = buffer;
endmodule

src/receiver/receiver_tb.v
`include "receiver.v"


module receiver_tb();
	reg RXD, clk, reset;
	wire rx_busy;
	receiver r1(
		.RXD(RXD),
		.clk(clk),
		.reset(reset)
	);


	initial begin
		$dumpfile("receiver_tb.vcd");
		$dumpvars(0,receiver_tb);
		clk = 0;
		RXD = 1;
		
		//bit de inicio
		#20 RXD = 0;

		//mensagem
		#20 RXD = 0;
		#20 RXD = 1;
		#20 RXD = 0;
		#20 RXD = 1;
		#20 RXD = 0;
		#20 RXD = 1;
		#20 RXD = 0;
		#20	RXD = 1;

		//bit de fim
		#20 RXD = 1;

		#200
		$finish;
		
	end
	always #10 clk =!clk;
endmodule

src/receiver/receiver_tb.vcd
$date
	Fri Jun 28 00:57:31 2019
$end
$version
	Icarus Verilog
$end
$timescale
	1s
$end
$scope module receiver_tb $end
$var reg 1 ! RXD $end
$var reg 1 " clk $end
$var reg 1 # reset $end
$scope module r1 $end
$var wire 1 ! RXD $end
$var wire 1 " clk $end
$var wire 1 # reset $end
$var wire 1 $ rx_busy $end
$var wire 8 % rx_data [0:7] $end
$var reg 8 & buffer [0:7] $end
$var reg 1 ' status $end
$var integer 32 ( count [31:0] $end
$upscope $end
$upscope $end
$enddefinitions $end
#0
$dumpvars
b0 (
0'
b0 &
b0 %
0$
x#
0"
1!
$end
#10
1"
#20
0"
0!
#30
1$
1'
1"
#40
0"
#50
b1 (
1"
#60
0"
1!
#70
b10 (
b1000000 %
b1000000 &
1"
#80
0"
0!
#90
b11 (
1"
#100
0"
1!
#110
b100 (
b1010000 %
b1010000 &
1"
#120
0"
0!
#130
b101 (
1"
#140
0"
1!
#150
b110 (
b1010100 %
b1010100 &
1"
#160
0"
0!
#170
b111 (
1"
#180
0"
1!
#190
b1000 (
b1010101 %
b1010101 &
1"
#200
0"
#210
0$
0'
1"
